{
    "role_1": "Mathematician_RoleType.ASSISTANT",
    "topic;": "Number theory",
    "sub_topic": "Discrete logarithm problem",
    "message_1": "Given that  ğ‘ is a primitive root of the prime number  ğ‘=23 , and that  ğ‘=12 is a residue modulo  ğ‘ , find an integer  ğ‘¥  such that  ğ‘ğ‘¥â‰¡ğ‘(mod 23) .",
    "message_2": "To find an integer x such that a^x â‰¡ b (mod 23), we need to use the discrete logarithm. Since a is a primitive root of the prime number p = 23, we know that a^x will generate all the non-zero residues modulo 23. \n\nWe can use trial and error to find the primitive root a. Let's try a = 2:\n\n2^1 â‰¡ 2 (mod 23)\n2^2 â‰¡ 4 (mod 23)\n2^3 â‰¡ 8 (mod 23)\n2^4 â‰¡ 16 (mod 23)\n2^5 â‰¡ 9 (mod 23)\n2^6 â‰¡ 18 (mod 23)\n2^7 â‰¡ 13 (mod 23)\n2^8 â‰¡ 3 (mod 23)\n2^9 â‰¡ 6 (mod 23)\n2^10 â‰¡ 12 (mod 23)\n...\n\nWe see that 2^10 â‰¡ 12 (mod 23), which means that a = 2 and x = 10 satisfy the given condition. Therefore, the integer x we are looking for is x = 10."
}