{
    "role_1": "Mathematician_RoleType.ASSISTANT",
    "topic;": "Linear algebra",
    "sub_topic": "Finding the determinant of a matrix",
    "message_1": "What is the determinant of the following 3x3 matrix?\n\n[2  3  4]\n[0  1  2]\n[1  2  1]",
    "message_2": "To find the determinant of a 3x3 matrix, we can use the following formula:\n\ndet(A) = a(ei - fh) - b(di - fg) + c(dh - eg)\n\nwhere a, b, c, d, e, f, g, h, and i are the elements of the matrix:\n\n[ a  b  c ]\n[ d  e  f ]\n[ g  h  i ]\n\nIn this case, the matrix is:\n\n[ 2  3  4 ]\n[ 0  1  2 ]\n[ 1  2  1 ]\n\nSo, a = 2, b = 3, c = 4, d = 0, e = 1, f = 2, g = 1, h = 2, and i = 1.\n\nNow, we can plug these values into the formula:\n\ndet(A) = 2(1*1 - 2*2) - 3(0*1 - 2*1) + 4(0*2 - 1*1)\ndet(A) = 2(-3) - 3(-2) + 4(-1)\ndet(A) = -6 + 6 - 4\ndet(A) = -4\n\nSo, the determinant of the given 3x3 matrix is -4."
}