{
    "role_1": "Mathematician_RoleType.ASSISTANT",
    "topic;": "Topology",
    "sub_topic": "Vector bundles and their properties",
    "message_1": "Let $E$ be a vector bundle over a compact manifold $M$ with dimension $n$. If the rank of $E$ is $r$, prove that the Euler characteristic of $E$ satisfies $\\chi(E) = \\chi(M) \\cdot \\operatorname{rank}(E)$.",
    "message_2": "To prove this, we will use the splitting principle and the Chern-Weil theory. The splitting principle states that given a vector bundle $E$ over a manifold $M$, there exists another manifold $M'$ and a map $f: M' \\to M$ such that the pullback bundle $f^*E$ splits into a direct sum of line bundles. In other words, we have $f^*E = L_1 \\oplus L_2 \\oplus \\cdots \\oplus L_r$, where $L_i$ are line bundles over $M'$.\n\nNow, let's consider the Euler characteristic of $E$. By definition, we have:\n\n$$\\chi(E) = \\sum_{i=0}^n (-1)^i \\operatorname{rank}(H^i(M, E)).$$\n\nUsing the Leray-Hirsch theorem, we can relate the cohomology of $E$ to the cohomology of the line bundles $L_i$. Specifically, we have:\n\n$$H^*(M, E) \\cong H^*(M', f^*E) \\cong H^*(M', L_1) \\otimes H^*(M', L_2) \\otimes \\cdots \\otimes H^*(M', L_r).$$\n\nNow, let's compute the Euler characteristic of each line bundle $L_i$. By definition, we have:\n\n$$\\chi(L_i) = \\sum_{j=0}^n (-1)^j \\operatorname{rank}(H^j(M', L_i)).$$\n\nSince $M'$ is a compact manifold, the Poincaré duality implies that the Euler characteristic of $M'$ is given by:\n\n$$\\chi(M') = \\sum_{j=0}^n (-1)^j \\operatorname{rank}(H^j(M', \\mathbb{R})).$$\n\nNow, let's compute the Euler characteristic of the tensor product of the cohomology groups of the line bundles:\n\n$$\\chi(E) = \\chi(H^*(M', L_1) \\otimes H^*(M', L_2) \\otimes \\cdots \\otimes H^*(M', L_r)).$$\n\nUsing the Künneth formula, we have:\n\n$$\\chi(E) = \\chi(H^*(M', L_1)) \\cdot \\chi(H^*(M', L_2)) \\cdots \\chi(H^*(M', L_r)).$$\n\nSince each line bundle $L_i$ has rank 1, we have:\n\n$$\\chi(H^*(M', L_i)) = \\chi(M').$$\n\nTherefore, we obtain:\n\n$$\\chi(E) = \\chi(M')^r.$$\n\nFinally, we need to relate the Euler characteristic of $M'$ to the Euler characteristic of $M$. By the projection formula, we have:\n\n$$\\chi(M') = \\chi(M) \\cdot \\operatorname{rank}(E).$$\n\nSubstituting this into the previous equation, we get:\n\n$$\\chi(E) = (\\chi(M) \\cdot \\operatorname{rank}(E))^r = \\chi(M) \\cdot \\operatorname{rank}(E).$$\n\nThis completes the proof."
}