{
    "role_1": "Mathematician_RoleType.ASSISTANT",
    "topic;": "Topology",
    "sub_topic": "Vector bundles and their properties",
    "message_1": "Find the Euler characteristic of the tangent bundle of the projective space $\\mathbb{RP}^2$.",
    "message_2": "To find the Euler characteristic of the tangent bundle of the projective space $\\mathbb{RP}^2$, we can use the following formula:\n\nEuler characteristic of the tangent bundle = Euler characteristic of the base space × Euler characteristic of the fiber.\n\nThe base space is $\\mathbb{RP}^2$, and the fiber is a 2-dimensional real vector space, which is homeomorphic to $\\mathbb{R}^2$.\n\nThe Euler characteristic of $\\mathbb{RP}^2$ is given by the formula:\n\nχ($\\mathbb{RP}^2$) = 1 + (-1)^2 + (-1)^4 = 1 + 1 + 1 = 3.\n\nThe Euler characteristic of $\\mathbb{R}^2$ is given by the formula:\n\nχ($\\mathbb{R}^2$) = 1 + (-1)^2 = 1 + 1 = 2.\n\nNow, we can compute the Euler characteristic of the tangent bundle:\n\nχ(T($\\mathbb{RP}^2$)) = χ($\\mathbb{RP}^2$) × χ($\\mathbb{R}^2$) = 3 × 2 = 6.\n\nTherefore, the Euler characteristic of the tangent bundle of the projective space $\\mathbb{RP}^2$ is 6."
}