{
    "role_1": "Mathematician_RoleType.ASSISTANT",
    "topic;": "Cryptography",
    "sub_topic": "ElGamal encryption and decryption",
    "message_1": "Suppose Bob wants to send a confidential message to Alice using ElGamal encryption with a public key (p=23, α=5, y=8). The message to be encrypted is m=16. \n1. Determine Bob's private key.\n2. Calculate the shared secret key between Bob and Alice.\n3. Encrypt the message using ElGamal encryption and the public key.\n4. Decrypt the ciphertext using ElGamal decryption and the shared secret key to get the original message.",
    "message_2": "1. Determine Bob's private key.\n\nIn ElGamal encryption, the private key (x) is not shared and is only known to the recipient (Alice). Therefore, we cannot determine Bob's private key.\n\n2. Calculate the shared secret key between Bob and Alice.\n\nTo calculate the shared secret key, Bob needs to choose a random number k (1 < k < p-1). Let's assume k = 6.\n\nNow, Bob calculates the shared secret key as K = y^k mod p = 8^6 mod 23 = 2.\n\n3. Encrypt the message using ElGamal encryption and the public key.\n\nTo encrypt the message m = 16, Bob computes the following two values:\n\nC1 = α^k mod p = 5^6 mod 23 = 10\nC2 = m * K mod p = 16 * 2 mod 23 = 9\n\nThe encrypted message (ciphertext) is the pair (C1, C2) = (10, 9).\n\n4. Decrypt the ciphertext using ElGamal decryption and the shared secret key to get the original message.\n\nTo decrypt the ciphertext, Alice calculates the shared secret key K' using her private key x:\n\nK' = C1^x mod p\n\nHowever, we don't know Alice's private key x, so we cannot calculate K' and decrypt the message. If we knew Alice's private key, we could calculate K', and then compute:\n\nm' = C2 * (K')^(-1) mod p\n\nwhere (K')^(-1) is the modular inverse of K' modulo p. This would give us the original message m'."
}