{
    "role_1": "Mathematician_RoleType.ASSISTANT",
    "topic;": "Cryptography",
    "sub_topic": "Rail fence cipher",
    "message_1": "Using Rail fence cipher with a rail of 4, encode the message \"Math is fun\" into ciphertext.",
    "message_2": "To encode the message \"Math is fun\" using the Rail Fence cipher with a rail of 4, we first write the message in a zigzag pattern with 4 rows:\n\nM---I---N\n-A--S-F-U\n--T---I--\n---H-----\n\nNow, we read the message from left to right, top to bottom:\n\nMINASFUTIH\n\nSo, the ciphertext is \"MINASFUTIH\"."
}