{
    "role_1": "Mathematician_RoleType.ASSISTANT",
    "topic;": "Fractal geometry",
    "sub_topic": "The Hausdorff dimension of the Vicsek fractal.",
    "message_1": "What is the Hausdorff dimension of the Vicsek fractal generated up to the 6th iteration, where each line segment has a length of 1 unit?",
    "message_2": "The Hausdorff dimension of the Vicsek fractal can be calculated using the formula:\n\nD = log(N) / log(s)\n\nwhere D is the Hausdorff dimension, N is the number of self-similar pieces, and s is the scaling factor.\n\nFor the Vicsek fractal, there are N = 5 self-similar pieces, and the scaling factor s = 3 (since each line segment is divided into 3 parts, and the middle part is removed).\n\nSo, the Hausdorff dimension of the Vicsek fractal is:\n\nD = log(5) / log(3) ≈ 1.465\n\nThis value is independent of the number of iterations, so the Hausdorff dimension of the Vicsek fractal generated up to the 6th iteration is still approximately 1.465."
}