{
    "role_1": "Mathematician_RoleType.ASSISTANT",
    "topic;": "Numerical analysis",
    "sub_topic": "Solving ordinary differential equations using Runge-Kutta methods",
    "message_1": "Consider the initial value problem:\n\ny' = 2xy\ny(0) = 1\n\nUsing the forth-order Runge-Kutta method with a step size of h=0.1, calculate an approximation of y(0.4).",
    "message_2": "To solve the initial value problem using the fourth-order Runge-Kutta method with a step size of h = 0.1, we will perform the following steps:\n\n1. Define the function f(x, y) = 2xy.\n2. Initialize the initial values: x0 = 0, y0 = 1, and h = 0.1.\n3. Perform 4 iterations (since we want to find y(0.4)).\n\nIn each iteration, we will calculate the following values:\n\nk1 = h * f(x0, y0)\nk2 = h * f(x0 + h/2, y0 + k1/2)\nk3 = h * f(x0 + h/2, y0 + k2/2)\nk4 = h * f(x0 + h, y0 + k3)\n\nThen, update the values of x0 and y0:\n\ny0 = y0 + (k1 + 2*k2 + 2*k3 + k4) / 6\nx0 = x0 + h\n\nAfter 4 iterations, the value of y0 will be an approximation of y(0.4).\n\nLet's perform the calculations:\n\nIteration 1:\nk1 = 0.1 * f(0, 1) = 0.1 * 2 * 0 * 1 = 0\nk2 = 0.1 * f(0.05, 1) = 0.1 * 2 * 0.05 * 1 = 0.01\nk3 = 0.1 * f(0.05, 1.005) = 0.1 * 2 * 0.05 * 1.005 = 0.0101\nk4 = 0.1 * f(0.1, 1.0101) = 0.1 * 2 * 0.1 * 1.0101 = 0.020202\ny1 = 1 + (0 + 2 * 0.01 + 2 * 0.0101 + 0.020202) / 6 = 1.0067\nx1 = 0 + 0.1 = 0.1\n\nIteration 2:\nk1 = 0.1 * f(0.1, 1.0067) = 0.1 * 2 * 0.1 * 1.0067 = 0.020134\nk2 = 0.1 * f(0.15, 1.0167) = 0.1 * 2 * 0.15 * 1.0167 = 0.030603\nk3 = 0.1 * f(0.15, 1.0217) = 0.1 * 2 * 0.15 * 1.0217 = 0.030906\nk4 = 0.1 * f(0.2, 1.0367) = 0.1 * 2 * 0.2 * 1.0367 = 0.041468\ny2 = 1.0067 + (0.020134 + 2 * 0.030603 + 2 * 0.030906 + 0.041468) / 6 = 1.0267\nx2 = 0.1 + 0.1 = 0.2\n\nIteration 3:\nk1 = 0.1 * f(0.2, 1.0267) = 0.1 * 2 * 0.2 * 1.0267 = 0.041068\nk2 = 0.1 * f(0.25, 1.0472) = 0.1 * 2 * 0.25 * 1.0472 = 0.05218\nk3 = 0.1 * f(0.25, 1.0522) = 0.1 * 2 * 0.25 * 1.0522 = 0.05255\nk4 = 0.1 * f(0.3, 1.0787) = 0.1 * 2 * 0.3 * 1.0787 = 0.063174\ny3 = 1.0267 + (0.041068 + 2 * 0.05218 + 2 * 0.05255 + 0.063174) / 6 = 1.0607\nx3 = 0.2 + 0.1 = 0.3\n\nIteration 4:\nk1 = 0.1 * f(0.3, 1.0607) = 0.1 * 2 * 0.3 * 1.0607 = 0.063642\nk2 = 0.1 * f(0.35, 1.0925) = 0.1 * 2 * 0.35 * 1.0925 = 0.076575\nk3 = 0.1 * f(0.35, 1.0975) = 0.1 * 2 * 0.35 * 1.0975 = 0.07695\nk4 = 0.1 * f(0.4, 1.1309) = 0.1 * 2 * 0.4 * 1.1309 = 0.090724\ny4 = 1.0607 + (0.063642 + 2 * 0.076575 + 2 * 0.07695 + 0.090724) / 6 = 1.1107\nx4 = 0.3 + 0.1 = 0.4\n\nSo, the approximation of y(0.4) using the fourth-order Runge-Kutta method with a step size of h = 0.1 is y4 ≈ 1.1107."
}