{
    "role_1": "Mathematician_RoleType.ASSISTANT",
    "topic;": "Fourier analysis",
    "sub_topic": "Using the Fourier transform to solve fluid dynamics problems",
    "message_1": "A tank of height 2 meters and small cross-sectional area contains a fluid. The fluid is introduced into the tank through a small hole at the top of the tank. Using the Fourier transform, derive an equation for the fluid free surface height as a function of time assuming the fluid enters the tank at a constant rate of 0.2 cubic meters per second. Take the fluid density to be 1000 kg/m³ and the hole diameter to be 5 mm. Also, assume that the fluid is inviscid and that the pressure at the hole is constant.",
    "message_2": "To derive an equation for the fluid free surface height as a function of time, we first need to establish the relationship between the fluid flow rate, the tank's cross-sectional area, and the height of the fluid in the tank. \n\nLet Q be the volumetric flow rate (0.2 m³/s), A_tank be the cross-sectional area of the tank, h(t) be the height of the fluid in the tank at time t, and ρ be the fluid density (1000 kg/m³). The hole diameter is 5 mm, but we don't need this information since the problem states that the fluid enters the tank at a constant rate.\n\nThe volume of the fluid in the tank at any time t is given by:\n\nV(t) = A_tank * h(t)\n\nSince the fluid enters the tank at a constant rate, the rate of change of the volume of the fluid in the tank is equal to the flow rate:\n\ndV(t)/dt = Q\n\nNow, differentiate the volume equation with respect to time:\n\nd(A_tank * h(t))/dt = A_tank * dh(t)/dt\n\nSubstitute the flow rate:\n\nA_tank * dh(t)/dt = Q\n\nNow, we can solve for the height of the fluid as a function of time:\n\ndh(t)/dt = Q / A_tank\n\nIntegrate both sides with respect to time:\n\n∫(dh(t)) = ∫(Q / A_tank) dt\n\nh(t) = (Q / A_tank) * t + C\n\nSince the tank is initially empty, the constant of integration C is 0:\n\nh(t) = (Q / A_tank) * t\n\nNow, we have derived the equation for the fluid free surface height as a function of time:\n\nh(t) = (0.2 m³/s) / A_tank * t\n\nThis equation gives the height of the fluid in the tank at any time t, assuming the fluid enters the tank at a constant rate of 0.2 cubic meters per second, the fluid density is 1000 kg/m³, and the pressure at the hole is constant."
}