{
    "role_1": "Mathematician_RoleType.ASSISTANT",
    "topic;": "Differential geometry",
    "sub_topic": "Determine the Laplacian of a function on a manifold.",
    "message_1": "Let $M$ be a 2-dimensional manifold with metric $g$, and let $f: M \\rightarrow \\mathbb{R}$ be a smooth function such that $f(x,y) = x^2 + y^2$ for all $(x,y) \\in M$. Determine the Laplacian of $f$ on $M$.",
    "message_2": "To compute the Laplacian of the function $f(x, y) = x^2 + y^2$ on the 2-dimensional manifold $M$ with metric $g$, we first need to compute the covariant derivatives of $f$. Let $(x^1, x^2)$ be local coordinates on $M$ such that $x^1 = x$ and $x^2 = y$. Then, the gradient of $f$ is given by:\n\n$\\nabla f = \\frac{\\partial f}{\\partial x^i} \\frac{\\partial}{\\partial x^i} = 2x \\frac{\\partial}{\\partial x} + 2y \\frac{\\partial}{\\partial y}$.\n\nNow, we compute the covariant derivative of the gradient of $f$:\n\n$\\nabla_i (\\nabla f) = \\nabla_i (2x \\frac{\\partial}{\\partial x} + 2y \\frac{\\partial}{\\partial y}) = 2 \\nabla_i (x \\frac{\\partial}{\\partial x}) + 2 \\nabla_i (y \\frac{\\partial}{\\partial y})$.\n\nUsing the product rule for covariant derivatives, we have:\n\n$\\nabla_i (x \\frac{\\partial}{\\partial x}) = (\\nabla_i x) \\frac{\\partial}{\\partial x} + x \\nabla_i (\\frac{\\partial}{\\partial x})$,\n\n$\\nabla_i (y \\frac{\\partial}{\\partial y}) = (\\nabla_i y) \\frac{\\partial}{\\partial y} + y \\nabla_i (\\frac{\\partial}{\\partial y})$.\n\nSince $x$ and $y$ are just coordinates, their covariant derivatives vanish:\n\n$\\nabla_i x = 0$, $\\nabla_i y = 0$.\n\nThus, we have:\n\n$\\nabla_i (\\nabla f) = 2x \\nabla_i (\\frac{\\partial}{\\partial x}) + 2y \\nabla_i (\\frac{\\partial}{\\partial y})$.\n\nFinally, we compute the Laplacian of $f$ as the contraction of the covariant derivative of the gradient of $f$:\n\n$\\Delta f = g^{ij} \\nabla_i (\\nabla f)_j = 2x g^{ij} \\nabla_i (\\frac{\\partial}{\\partial x})_j + 2y g^{ij} \\nabla_i (\\frac{\\partial}{\\partial y})_j$.\n\nSince the metric $g$ is not specified, we cannot compute the explicit form of the Laplacian of $f$. However, we can express it in terms of the metric components and their derivatives as follows:\n\n$\\Delta f = 2x g^{ij} \\nabla_i (\\frac{\\partial}{\\partial x})_j + 2y g^{ij} \\nabla_i (\\frac{\\partial}{\\partial y})_j$."
}